instagram_sync/__init__.py
instagram_sync/contrib/__init__.py
instagram_sync/contrib/django/__init__.py
instagram_sync/contrib/django/admin.py
instagram_sync/contrib/django/apps.py
instagram_sync/contrib/django/migrations/0001_initial.py
instagram_sync/contrib/django/migrations/__init__.py
instagram_sync/contrib/django/models.py
instagram_sync/contrib/django/storage.py
instagram_sync/contrib/django/templates/instagram_sync/add_form.html
instagram_sync/contrib/django/templates/instagram_sync/dynamic_fieldsets.html
instagram_sync/contrib/django/tests.py
instagram_sync/contrib/django/views.py
instagram_sync/core/__init__.py
instagram_sync/core/graph_api/__init__.py
instagram_sync/core/graph_api/auth.py
instagram_sync/core/graph_api/instagram.py
instagram_sync/core/graph_api/pages.py
instagram_sync/core/media.py
instagram_sync/core/requests.py
instagram_sync/core/settings.py
instagram_sync/core/utils.py
instagram_sync-0.1.8.dist-info/WHEEL
instagram_sync-0.1.8.dist-info/METADATA
instagram_sync-0.1.8.dist-info/RECORD
