Metadata-Version: 2.1
Name: instagram-sync
Version: 0.1.8
Summary: 
Author: MJ Hardin
Author-email: mhardinla@gmail.com
Requires-Python: >=3.9,<4.0
Classifier: Programming Language :: Python :: 3
Classifier: Programming Language :: Python :: 3.10
Classifier: Programming Language :: Python :: 3.9
Provides-Extra: django
Requires-Dist: Django (>=3.0); extra == "django"
Requires-Dist: django-encrypted-model-fields (>=0.6.5,<0.7.0); extra == "django"
Requires-Dist: requests (>=2.28.1,<3.0.0)
